pygedreader/__init__.py
pygedreader/cli.py
pygedreader/models/__init__.py
pygedreader/models/base.py
pygedreader/models/date.py
pygedreader/models/event.py
pygedreader/models/family.py
pygedreader/models/gedcom.py
pygedreader/models/header.py
pygedreader/models/individual.py
pygedreader/models/media.py
pygedreader/models/name.py
pygedreader/models/note.py
pygedreader/models/place.py
pygedreader/models/repository.py
pygedreader/models/source.py
pygedreader/models/source_citation.py
pygedreader/models/submitter.py
pygedreader/parser/__init__.py
pygedreader/parser/parser.py
pygedreader/parser/record_parser.py
pygedreader/parser/tokenizer.py
pygedreader/parser/tree.py
pygedreader-0.1.0.dist-info/METADATA
pygedreader-0.1.0.dist-info/WHEEL
pygedreader-0.1.0.dist-info/entry_points.txt
pygedreader-0.1.0.dist-info/licenses/LICENSE
pygedreader-0.1.0.dist-info/RECORD
