Metadata-Version: 2.4
Name: pygedreader
Version: 0.1.0
Summary: A Python library for parsing GEDCOM files with Ancestry.com export support
Project-URL: Homepage, https://github.com/creising/pygedreader
Project-URL: Repository, https://github.com/creising/pygedreader
Project-URL: Issues, https://github.com/creising/pygedreader/issues
Author: creising
License-Expression: MIT
License-File: LICENSE
Keywords: ancestry,family-tree,gedcom,genealogy,parser
Classifier: Development Status :: 4 - Beta
Classifier: Intended Audience :: Developers
Classifier: License :: OSI Approved :: MIT License
Classifier: Programming Language :: Python :: 3
Classifier: Programming Language :: Python :: 3.14
Classifier: Topic :: Sociology :: Genealogy
Requires-Python: >=3.14
Requires-Dist: pydantic>=2.12.5
